colorbox/__init__.py
colorbox/apps.py
colorbox/decorators.py
colorbox/forms.py
colorbox/http.py
colorbox/utils.py
colorbox/views.py
colorbox/static/css/colorbox.css
colorbox/static/css/images/border.png
colorbox/static/css/images/controls.png
colorbox/static/css/images/loading.gif
colorbox/static/css/images/loading_background.png
colorbox/static/css/images/overlay.png
colorbox/static/css/images/ie6/borderBottomCenter.png
colorbox/static/css/images/ie6/borderBottomLeft.png
colorbox/static/css/images/ie6/borderBottomRight.png
colorbox/static/css/images/ie6/borderMiddleLeft.png
colorbox/static/css/images/ie6/borderMiddleRight.png
colorbox/static/css/images/ie6/borderTopCenter.png
colorbox/static/css/images/ie6/borderTopLeft.png
colorbox/static/css/images/ie6/borderTopRight.png
colorbox/static/js/colorbox.coop.js
colorbox/static/js/jquery.colorbox-min.js
colorbox/static/js/jquery.colorbox.js
colorbox/static/js/jquery.form.js
colorbox/static/js/i18n/jquery.colorbox-ar.js
colorbox/static/js/i18n/jquery.colorbox-bg.js
colorbox/static/js/i18n/jquery.colorbox-bn.js
colorbox/static/js/i18n/jquery.colorbox-ca.js
colorbox/static/js/i18n/jquery.colorbox-cs.js
colorbox/static/js/i18n/jquery.colorbox-da.js
colorbox/static/js/i18n/jquery.colorbox-de.js
colorbox/static/js/i18n/jquery.colorbox-es.js
colorbox/static/js/i18n/jquery.colorbox-et.js
colorbox/static/js/i18n/jquery.colorbox-fa.js
colorbox/static/js/i18n/jquery.colorbox-fi.js
colorbox/static/js/i18n/jquery.colorbox-fr.js
colorbox/static/js/i18n/jquery.colorbox-gl.js
colorbox/static/js/i18n/jquery.colorbox-gr.js
colorbox/static/js/i18n/jquery.colorbox-he.js
colorbox/static/js/i18n/jquery.colorbox-hr.js
colorbox/static/js/i18n/jquery.colorbox-hu.js
colorbox/static/js/i18n/jquery.colorbox-id.js
colorbox/static/js/i18n/jquery.colorbox-it.js
colorbox/static/js/i18n/jquery.colorbox-ja.js
colorbox/static/js/i18n/jquery.colorbox-kr.js
colorbox/static/js/i18n/jquery.colorbox-lt.js
colorbox/static/js/i18n/jquery.colorbox-lv.js
apidev_coop_colorbox-1.6.0.dist-info/METADATA
apidev_coop_colorbox-1.6.0.dist-info/WHEEL
apidev_coop_colorbox-1.6.0.dist-info/top_level.txt
apidev_coop_colorbox-1.6.0.dist-info/RECORD
