Metadata-Version: 2.1
Name: apidev-coop-colorbox
Version: 1.6.0
Summary: Manage colorbox popup for django
Home-page: https://github.com/ljean/coop-colorbox/
Download-URL: https://github.com/ljean/coop-colorbox/tarball/master
Author: Luc Jean
Author-email: ljean@apidev.fr
License: BSD
Classifier: Development Status :: 5 - Production/Stable
Classifier: Environment :: Web Environment
Classifier: Intended Audience :: Developers
Classifier: License :: OSI Approved :: BSD License
Classifier: Operating System :: OS Independent
Classifier: Programming Language :: Python
Classifier: Framework :: Django
Classifier: Natural Language :: English
Classifier: Natural Language :: French
Classifier: Topic :: Internet :: WWW/HTTP :: Dynamic Content
Classifier: Topic :: Internet :: WWW/HTTP :: WSGI :: Application
